stimwrap/__init__.py
stimwrap/_stim_functions.py
stimwrap/_stimwrap.py
stimwrap-0.3.0.dist-info/LICENSE
stimwrap-0.3.0.dist-info/METADATA
stimwrap-0.3.0.dist-info/WHEEL
stimwrap-0.3.0.dist-info/top_level.txt
stimwrap-0.3.0.dist-info/RECORD
