Metadata-Version: 2.1
Name: stimwrap
Version: 0.3.0
Summary: Stimwrap: a Python interface for STIM
Home-page: https://github.com/rajewsky-lab/stimwrap
Author: Nikos Karaiskos
Author-email: nikolaos.karaiskos@mdc-berlin.de
License: MIT
Project-URL: Bug Tracker, https://github.com/rajewsky-lab/stimwrap/issues
Classifier: Programming Language :: Python :: 3
Classifier: License :: OSI Approved :: GNU General Public License v2 or later (GPLv2+)
Classifier: Operating System :: OS Independent
Requires-Python: >=3.9
License-File: LICENSE
Requires-Dist: numpy
Requires-Dist: h5py
Requires-Dist: zarr (==2.18.2)
